SelFw/__init__.py
SelFw/abrir.py
SelFw/configchrome.py
SelFw/js.py
SelFw/utils.py
SelFw/xpath.py
selfw-0.2.7.dist-info/METADATA
selfw-0.2.7.dist-info/WHEEL
selfw-0.2.7.dist-info/top_level.txt
selfw-0.2.7.dist-info/RECORD
