Metadata-Version: 2.4
Name: selfw
Version: 0.2.7
Summary: Un framework Selenium para automatizar pruebas de forma simple
Author-email: Iván <ggivixd@gmail.com>
License: MIT
Project-URL: Homepage, https://pypi.org/user/ivanbp/
Requires-Python: >=3.8
Requires-Dist: selenium>=4.0.0
Requires-Dist: pytest
